surface_saver/__init__.py
surface_saver/__main__.py
surface_saver/box-contents-schema.json
surface_saver/validator.py
surface_saver/tests/__init__.py
surface_saver/tests/test_init.py
surface_saver/tests/test_validator.py
surface_saver-2024.7.7.68985.dist-info/METADATA
surface_saver-2024.7.7.68985.dist-info/WHEEL
surface_saver-2024.7.7.68985.dist-info/entry_points.txt
surface_saver-2024.7.7.68985.dist-info/top_level.txt
surface_saver-2024.7.7.68985.dist-info/RECORD
