Metadata-Version: 2.1
Name: surface_saver
Version: 2024.7.7.68985
Summary: Help to box up the stuff that's cluttering horizontal surfaces 
Author-email: Moshe Zadka <moshez@zadka.club>
License: Permission is hereby granted, free of charge, to any person obtaining a
Project-URL: Homepage, https://github.com/moshez/surface_saver
Requires-Dist: gather
Requires-Dist: jsonschema
Requires-Dist: commander-data
Provides-Extra: doc
Requires-Dist: sphinx ; extra == 'doc'
Provides-Extra: docs
Requires-Dist: sphinx ; extra == 'docs'
Provides-Extra: lint
Requires-Dist: flake8 ; extra == 'lint'
Requires-Dist: black ; extra == 'lint'
Provides-Extra: mypy
Requires-Dist: mypy ; extra == 'mypy'
Provides-Extra: test
Requires-Dist: coverage ; extra == 'test'
Requires-Dist: virtue ; extra == 'test'
Provides-Extra: tests
Requires-Dist: virtue ; extra == 'tests'
Requires-Dist: pyhamcrest ; extra == 'tests'
Requires-Dist: coverage ; extra == 'tests'
